collada2obj/ColladaFileConverter.py
collada2obj/MeshConverter.py
collada2obj/TechniqueCommon.py
collada2obj/__init__.py
collada2obj-0.1.2.dist-info/LICENSE
collada2obj-0.1.2.dist-info/METADATA
collada2obj-0.1.2.dist-info/WHEEL
collada2obj-0.1.2.dist-info/top_level.txt
collada2obj-0.1.2.dist-info/RECORD
