Metadata-Version: 2.1
Name: collada2obj
Version: 0.1.2
Summary: A library that can be used to easily convert a collada file (.dae) to a wavefront file (.obj).
Home-page: https://github.com/kwesiRutledge/collada2obj
Author: Kwesi Rutledge
Author-email: thesolitaryecrivain@gmail.com
Keywords: robotics,3D Modelling,dae,obj
License-File: LICENSE
Requires-Dist: ipdb
Requires-Dist: typer
Requires-Dist: numpy
